{
  "collectionName": "components_sections_partners",
  "info": {
    "displayName": "Partners",
    "icon": "chartBubble",
    "description": ""
  },
  "options": {},
  "attributes": {
    "title": {
      "type": "string",
      "maxLength": 255,
      "required": true
    },
    "image": {
      "type": "media",
      "multiple": false,
      "required": true,
      "allowedTypes": [
        "images"
      ]
    },
    "description": {
      "type": "text",
      "maxLength": 1000,
      "required": true
    },
    "link": {
      "type": "component",
      "component": "repeatable.anchor",
      "repeatable": false,
      "required": true
    }
  }
}
